pubsub_worker/__init__.py
pubsub_worker-0.1.0.dist-info/WHEEL
pubsub_worker-0.1.0.dist-info/METADATA
pubsub_worker-0.1.0.dist-info/RECORD
