Metadata-Version: 2.1
Name: pubsub-worker
Version: 0.1.0
Summary: 
License: MIT
Author: Jacob Hayes
Author-email: jacob.r.hayes@gmail.com
Requires-Python: >=3.7,<4.0
Classifier: License :: OSI Approved :: MIT License
Classifier: Programming Language :: Python :: 3
Classifier: Programming Language :: Python :: 3.7
Requires-Dist: google-cloud-pubsub (>=1.2,<2.0)
